PicoMusic-0.1.0.dev4.dist-info/DESCRIPTION.rst
PicoMusic-0.1.0.dev4.dist-info/METADATA
PicoMusic-0.1.0.dev4.dist-info/RECORD
PicoMusic-0.1.0.dev4.dist-info/WHEEL
PicoMusic-0.1.0.dev4.dist-info/entry_points.txt
PicoMusic-0.1.0.dev4.dist-info/metadata.json
PicoMusic-0.1.0.dev4.dist-info/top_level.txt
picomusic/__init__.py
picomusic/chord.py
picomusic/lengths.py
picomusic/note.py
picomusic/part.py
picomusic/phrase.py
picomusic/stage.py
picomusic/stagemanager.py
picomusic/sunvoxproject.py
picomusic/sunvoxsource.py
picomusic/timeline.py
picomusic/scripts/__init__.py
picomusic/scripts/picomusic.py
picomusic/tunings/__init__.py
picomusic/tunings/drumkit.py
picomusic/tunings/equal_temperament.py
picomusic/tunings/pitch.py
picomusic/utils/__init__.py
picomusic/utils/singleton.py
picomusic/utils/terminalwidth.py
picomusic/voices/__init__.py
picomusic/voices/basickit.py
picomusic/voices/basickit.sunvox
picomusic/voices/piano.py
picomusic/voices/piano.sunsynth
picomusic/voices/sunvoxvoice.py
picomusic/voices/voice.py
