Metadata-Version: 2.0
Name: PicoMusic
Version: 0.1.0.dev4
Summary: UNKNOWN
Home-page: https://github.com/metrasynth/picomusic
Author: Matthew Scott
Author-email: matt@11craft.com
License: MIT
Project-URL: Documentation, https://picomusic.readthedocs.io/en/latest/
Project-URL: Funding, https://www.patreon.com/queries
Project-URL: Source, https://github.com/metrasynth/picomusic
Project-URL: Tracker, https://github.com/metrasynth/picomusic/issues
Keywords: music sunvox learning
Platform: any
Classifier: Development Status :: 3 - Alpha
Classifier: Environment :: Console
Classifier: Environment :: Other Environment
Classifier: Framework :: IPython
Classifier: Intended Audience :: Education
Classifier: License :: OSI Approved :: MIT License
Classifier: Operating System :: MacOS :: MacOS X
Classifier: Operating System :: Microsoft :: Windows
Classifier: Operating System :: POSIX :: Linux
Classifier: Programming Language :: Python
Classifier: Programming Language :: Python :: 3 :: Only
Classifier: Programming Language :: Python :: 3.6
Classifier: Programming Language :: Python :: Implementation :: CPython
Classifier: Topic :: Artistic Software
Classifier: Topic :: Education
Classifier: Topic :: Multimedia :: Sound/Audio :: Sound Synthesis
Requires-Python: ~=3.6
Requires-Dist: begins (>=0.9)
Requires-Dist: ipython (>=6.2.1)
Requires-Dist: py (>=1.5.2)
Requires-Dist: pyglet (>=1.3.1)
Requires-Dist: radiant-voices (>=0.4.0.dev2)
Requires-Dist: sunvox-dll-python (>=0.2.1.1.9.3.2)
